{"schema_version":"1.0","date":"2026-08-09","games":[{"id":"2026-08-09-cin-wsh","mlb_game_pk":822700,"date":"2026-08-09","game_time":"2026-08-09T16:15:00Z","sport":"MLB","status":"scheduled","venue":{"id":3309,"name":"Nationals Park"},"away_team":{"abbr":"CIN","name":"Cincinnati Reds","team_id":113},"home_team":{"abbr":"WSH","name":"Washington Nationals","team_id":120},"pitchers":{"away":{"id":null,"name":"Starter TBD","status":"unknown","age":null,"throws":null,"profile_url":"#","stats":{"last_30":{},"season":{}}},"home":{"id":null,"name":"Starter TBD","status":"unknown","age":null,"throws":null,"profile_url":"#","stats":{"last_30":{},"season":{}}}},"lineups":{},"pitcher_vs_lineup":{},"bullpens":{},"weather":{},"market":{},"controls":{"default_timeframe":"last_30","default_location":"all"}},{"id":"2026-08-09-ath-bos","mlb_game_pk":824724,"date":"2026-08-09","game_time":"2026-08-09T17:35:00Z","sport":"MLB","status":"scheduled","venue":{"id":3,"name":"Fenway Park"},"away_team":{"abbr":"ATH","name":"Athletics","team_id":133},"home_team":{"abbr":"BOS","name":"Boston Red Sox","team_id":111},"pitchers":{"away":{"id":null,"name":"Starter TBD","status":"unknown","age":null,"throws":null,"profile_url":"#","stats":{"last_30":{},"season":{}}},"home":{"id":null,"name":"Starter TBD","status":"unknown","age":null,"throws":null,"profile_url":"#","stats":{"last_30":{},"season":{}}}},"lineups":{},"pitcher_vs_lineup":{},"bullpens":{},"weather":{},"market":{},"controls":{"default_timeframe":"last_30","default_location":"all"}},{"id":"2026-08-09-atl-nyy","mlb_game_pk":823513,"date":"2026-08-09","game_time":"2026-08-09T17:35:00Z","sport":"MLB","status":"scheduled","venue":{"id":3313,"name":"Yankee Stadium"},"away_team":{"abbr":"ATL","name":"Atlanta Braves","team_id":144},"home_team":{"abbr":"NYY","name":"New York Yankees","team_id":147},"pitchers":{"away":{"id":null,"name":"Starter TBD","status":"unknown","age":null,"throws":null,"profile_url":"#","stats":{"last_30":{},"season":{}}},"home":{"id":null,"name":"Starter TBD","status":"unknown","age":null,"throws":null,"profile_url":"#","stats":{"last_30":{},"season":{}}}},"lineups":{},"pitcher_vs_lineup":{},"bullpens":{},"weather":{},"market":{},"controls":{"default_timeframe":"last_30","default_location":"all"}},{"id":"2026-08-09-nym-pit","mlb_game_pk":823345,"date":"2026-08-09","game_time":"2026-08-09T17:35:00Z","sport":"MLB","status":"scheduled","venue":{"id":31,"name":"PNC Park"},"away_team":{"abbr":"NYM","name":"New York Mets","team_id":121},"home_team":{"abbr":"PIT","name":"Pittsburgh Pirates","team_id":134},"pitchers":{"away":{"id":null,"name":"Starter TBD","status":"unknown","age":null,"throws":null,"profile_url":"#","stats":{"last_30":{},"season":{}}},"home":{"id":null,"name":"Starter TBD","status":"unknown","age":null,"throws":null,"profile_url":"#","stats":{"last_30":{},"season":{}}}},"lineups":{},"pitcher_vs_lineup":{},"bullpens":{},"weather":{},"market":{},"controls":{"default_timeframe":"last_30","default_location":"all"}},{"id":"2026-08-09-tor-phi","mlb_game_pk":823425,"date":"2026-08-09","game_time":"2026-08-09T17:35:00Z","sport":"MLB","status":"scheduled","venue":{"id":2681,"name":"Citizens Bank Park"},"away_team":{"abbr":"TOR","name":"Toronto Blue Jays","team_id":141},"home_team":{"abbr":"PHI","name":"Philadelphia Phillies","team_id":143},"pitchers":{"away":{"id":null,"name":"Starter TBD","status":"unknown","age":null,"throws":null,"profile_url":"#","stats":{"last_30":{},"season":{}}},"home":{"id":null,"name":"Starter TBD","status":"unknown","age":null,"throws":null,"profile_url":"#","stats":{"last_30":{},"season":{}}}},"lineups":{},"pitcher_vs_lineup":{},"bullpens":{},"weather":{},"market":{},"controls":{"default_timeframe":"last_30","default_location":"all"}},{"id":"2026-08-09-laa-mia","mlb_game_pk":823835,"date":"2026-08-09","game_time":"2026-08-09T17:40:00Z","sport":"MLB","status":"scheduled","venue":{"id":4169,"name":"loanDepot park"},"away_team":{"abbr":"LAA","name":"Los Angeles Angels","team_id":108},"home_team":{"abbr":"MIA","name":"Miami Marlins","team_id":146},"pitchers":{"away":{"id":null,"name":"Starter TBD","status":"unknown","age":null,"throws":null,"profile_url":"#","stats":{"last_30":{},"season":{}}},"home":{"id":null,"name":"Starter TBD","status":"unknown","age":null,"throws":null,"profile_url":"#","stats":{"last_30":{},"season":{}}}},"lineups":{},"pitcher_vs_lineup":{},"bullpens":{},"weather":{},"market":{},"controls":{"default_timeframe":"last_30","default_location":"all"}},{"id":"2026-08-09-chc-kc","mlb_game_pk":824078,"date":"2026-08-09","game_time":"2026-08-09T18:10:00Z","sport":"MLB","status":"scheduled","venue":{"id":7,"name":"Kauffman Stadium"},"away_team":{"abbr":"CHC","name":"Chicago Cubs","team_id":112},"home_team":{"abbr":"KC","name":"Kansas City Royals","team_id":118},"pitchers":{"away":{"id":null,"name":"Starter TBD","status":"unknown","age":null,"throws":null,"profile_url":"#","stats":{"last_30":{},"season":{}}},"home":{"id":null,"name":"Starter TBD","status":"unknown","age":null,"throws":null,"profile_url":"#","stats":{"last_30":{},"season":{}}}},"lineups":{},"pitcher_vs_lineup":{},"bullpens":{},"weather":{},"market":{},"controls":{"default_timeframe":"last_30","default_location":"all"}},{"id":"2026-08-09-cle-cws","mlb_game_pk":824564,"date":"2026-08-09","game_time":"2026-08-09T18:10:00Z","sport":"MLB","status":"scheduled","venue":{"id":4,"name":"Rate Field"},"away_team":{"abbr":"CLE","name":"Cleveland Guardians","team_id":114},"home_team":{"abbr":"CWS","name":"Chicago White Sox","team_id":145},"pitchers":{"away":{"id":null,"name":"Starter TBD","status":"unknown","age":null,"throws":null,"profile_url":"#","stats":{"last_30":{},"season":{}}},"home":{"id":null,"name":"Starter TBD","status":"unknown","age":null,"throws":null,"profile_url":"#","stats":{"last_30":{},"season":{}}}},"lineups":{},"pitcher_vs_lineup":{},"bullpens":{},"weather":{},"market":{},"controls":{"default_timeframe":"last_30","default_location":"all"}},{"id":"2026-08-09-min-mil","mlb_game_pk":823751,"date":"2026-08-09","game_time":"2026-08-09T18:10:00Z","sport":"MLB","status":"scheduled","venue":{"id":32,"name":"American Family Field"},"away_team":{"abbr":"MIN","name":"Minnesota Twins","team_id":142},"home_team":{"abbr":"MIL","name":"Milwaukee Brewers","team_id":158},"pitchers":{"away":{"id":null,"name":"Starter TBD","status":"unknown","age":null,"throws":null,"profile_url":"#","stats":{"last_30":{},"season":{}}},"home":{"id":null,"name":"Starter TBD","status":"unknown","age":null,"throws":null,"profile_url":"#","stats":{"last_30":{},"season":{}}}},"lineups":{},"pitcher_vs_lineup":{},"bullpens":{},"weather":{},"market":{},"controls":{"default_timeframe":"last_30","default_location":"all"}},{"id":"2026-08-09-col-stl","mlb_game_pk":823020,"date":"2026-08-09","game_time":"2026-08-09T18:15:00Z","sport":"MLB","status":"scheduled","venue":{"id":2889,"name":"Busch Stadium"},"away_team":{"abbr":"COL","name":"Colorado Rockies","team_id":115},"home_team":{"abbr":"STL","name":"St. Louis Cardinals","team_id":138},"pitchers":{"away":{"id":null,"name":"Starter TBD","status":"unknown","age":null,"throws":null,"profile_url":"#","stats":{"last_30":{},"season":{}}},"home":{"id":null,"name":"Starter TBD","status":"unknown","age":null,"throws":null,"profile_url":"#","stats":{"last_30":{},"season":{}}}},"lineups":{},"pitcher_vs_lineup":{},"bullpens":{},"weather":{},"market":{},"controls":{"default_timeframe":"last_30","default_location":"all"}},{"id":"2026-08-09-bal-tex","mlb_game_pk":822862,"date":"2026-08-09","game_time":"2026-08-09T18:35:00Z","sport":"MLB","status":"scheduled","venue":{"id":5325,"name":"Globe Life Field"},"away_team":{"abbr":"BAL","name":"Baltimore Orioles","team_id":110},"home_team":{"abbr":"TEX","name":"Texas Rangers","team_id":140},"pitchers":{"away":{"id":null,"name":"Starter TBD","status":"unknown","age":null,"throws":null,"profile_url":"#","stats":{"last_30":{},"season":{}}},"home":{"id":null,"name":"Starter TBD","status":"unknown","age":null,"throws":null,"profile_url":"#","stats":{"last_30":{},"season":{}}}},"lineups":{},"pitcher_vs_lineup":{},"bullpens":{},"weather":{},"market":{},"controls":{"default_timeframe":"last_30","default_location":"all"}},{"id":"2026-08-09-det-sfg","mlb_game_pk":823190,"date":"2026-08-09","game_time":"2026-08-09T20:05:00Z","sport":"MLB","status":"scheduled","venue":{"id":2395,"name":"Oracle Park"},"away_team":{"abbr":"DET","name":"Detroit Tigers","team_id":116},"home_team":{"abbr":"SFG","name":"San Francisco Giants","team_id":137},"pitchers":{"away":{"id":null,"name":"Starter TBD","status":"unknown","age":null,"throws":null,"profile_url":"#","stats":{"last_30":{},"season":{}}},"home":{"id":null,"name":"Starter TBD","status":"unknown","age":null,"throws":null,"profile_url":"#","stats":{"last_30":{},"season":{}}}},"lineups":{},"pitcher_vs_lineup":{},"bullpens":{},"weather":{},"market":{},"controls":{"default_timeframe":"last_30","default_location":"all"}},{"id":"2026-08-09-lad-ari","mlb_game_pk":825050,"date":"2026-08-09","game_time":"2026-08-09T20:10:00Z","sport":"MLB","status":"scheduled","venue":{"id":15,"name":"Chase Field"},"away_team":{"abbr":"LAD","name":"Los Angeles Dodgers","team_id":119},"home_team":{"abbr":"ARI","name":"Arizona Diamondbacks","team_id":109},"pitchers":{"away":{"id":null,"name":"Starter TBD","status":"unknown","age":null,"throws":null,"profile_url":"#","stats":{"last_30":{},"season":{}}},"home":{"id":null,"name":"Starter TBD","status":"unknown","age":null,"throws":null,"profile_url":"#","stats":{"last_30":{},"season":{}}}},"lineups":{},"pitcher_vs_lineup":{},"bullpens":{},"weather":{},"market":{},"controls":{"default_timeframe":"last_30","default_location":"all"}},{"id":"2026-08-09-tb-sea","mlb_game_pk":823104,"date":"2026-08-09","game_time":"2026-08-09T20:10:00Z","sport":"MLB","status":"scheduled","venue":{"id":680,"name":"T-Mobile Park"},"away_team":{"abbr":"TB","name":"Tampa Bay Rays","team_id":139},"home_team":{"abbr":"SEA","name":"Seattle Mariners","team_id":136},"pitchers":{"away":{"id":null,"name":"Starter TBD","status":"unknown","age":null,"throws":null,"profile_url":"#","stats":{"last_30":{},"season":{}}},"home":{"id":null,"name":"Starter TBD","status":"unknown","age":null,"throws":null,"profile_url":"#","stats":{"last_30":{},"season":{}}}},"lineups":{},"pitcher_vs_lineup":{},"bullpens":{},"weather":{},"market":{},"controls":{"default_timeframe":"last_30","default_location":"all"}},{"id":"2026-08-09-hou-sd","mlb_game_pk":823268,"date":"2026-08-09","game_time":"2026-08-10T00:20:00Z","sport":"MLB","status":"scheduled","venue":{"id":2680,"name":"Petco Park"},"away_team":{"abbr":"HOU","name":"Houston Astros","team_id":117},"home_team":{"abbr":"SD","name":"San Diego Padres","team_id":135},"pitchers":{"away":{"id":null,"name":"Starter TBD","status":"unknown","age":null,"throws":null,"profile_url":"#","stats":{"last_30":{},"season":{}}},"home":{"id":null,"name":"Starter TBD","status":"unknown","age":null,"throws":null,"profile_url":"#","stats":{"last_30":{},"season":{}}}},"lineups":{},"pitcher_vs_lineup":{},"bullpens":{},"weather":{},"market":{},"controls":{"default_timeframe":"last_30","default_location":"all"}}]}